morx-0.1.1.dist-info/METADATA
morx-0.1.1.dist-info/WHEEL
morx/__init__.py
morx/morx.cpython-39-x86_64-linux-gnu.so
morx-0.1.1.dist-info/RECORD
