Metadata-Version: 2.1
Name: morx
Version: 0.1.1
Summary: 通用图像配准库--python 接口
